{
  "timestamp": "2025-10-10T18:35:54.793038",
  "aura_score": 49.4,
  "energy_score": 62.4,
  "skin_score": 20.5,
  "stress_score": 69.0,
  "trends": [
    "Первый анализ! Данные для трендов появятся после следующего скана."
  ],
  "recommendations": [
    "💤 Energy низкий: уделите внимание качеству сна и гидратации",
    "🌟 Skin требует ухода: используйте увлажняющие средства",
    "🧘‍♂️ Stress повышен: попробуйте техники релаксации"
  ],
  "scan_type": "single"
}